cocode/__init__.py
cocode/common.py
cocode/exceptions.py
cocode/py.typed
cocode/utils.py
cocode/validation_cli.py
cocode/cli/__init__.py
cocode/cli/__main__.py
cocode/cli/main.py
cocode/cli/ai_instructions/__init__.py
cocode/cli/ai_instructions/ai_instructions_cli.py
cocode/cli/analyze/__init__.py
cocode/cli/analyze/analyze_cli.py
cocode/cli/changelog/__init__.py
cocode/cli/changelog/changelog_cli.py
cocode/cli/doc/__init__.py
cocode/cli/doc/doc_cli.py
cocode/cli/features/__init__.py
cocode/cli/features/features_cli.py
cocode/cli/repo/__init__.py
cocode/cli/repo/repo_cli.py
cocode/github/__init__.py
cocode/github/github_cli.py
cocode/github/github_repo_manager.py
cocode/github/github_wrapper.py
cocode/pipelines/__init__.py
cocode/pipelines/text_utils.plx
cocode/pipelines/text_utils.py
cocode/pipelines/doc_proofread/__init__.py
cocode/pipelines/doc_proofread/doc_proofread.plx
cocode/pipelines/doc_proofread/doc_proofread_models.py
cocode/pipelines/doc_proofread/file_utils.py
cocode/pipelines/doc_update/__init__.py
cocode/pipelines/doc_update/ai_instruction_update.plx
cocode/pipelines/doc_update/doc_update.plx
cocode/pipelines/doc_update/doc_update_models.py
cocode/pipelines/swe_diff/changelog.plx
cocode/pipelines/swe_diff/changelog_enhanced.plx
cocode/pipelines/swe_diff/changelog_struct.py
cocode/pipelines/swe_diff/git.plx
cocode/pipelines/swe_docs/__init__.py
cocode/pipelines/swe_docs/swe_docs.plx
cocode/pipelines/swe_docs/swe_docs.py
cocode/repox/models.py
cocode/repox/process_python.py
cocode/repox/repox_cli.py
cocode/repox/repox_cmd.py
cocode/repox/repox_formatters.py
cocode/repox/repox_processor.py
cocode/swe/swe_cmd.py
cocode/swe/swe_utils.py
pipelex.toml
cocode-0.6.1.dist-info/METADATA
cocode-0.6.1.dist-info/WHEEL
cocode-0.6.1.dist-info/entry_points.txt
cocode-0.6.1.dist-info/licenses/LICENSE
cocode-0.6.1.dist-info/RECORD
