Metadata-Version: 2.4
Name: cocode
Version: 0.6.1
Summary: Cocode is the friend of your code
Project-URL: Homepage, https://pipelex.com
Project-URL: Repository, https://github.com/pipelex/cocode
Project-URL: Documentation, https://docs.pipelex.com/
Author-email: "Evotis S.A.S." <evotis@pipelex.com>
Maintainer-email: Pipelex staff <oss@pipelex.com>
License-Expression: MIT
License-File: LICENSE
Classifier: Operating System :: OS Independent
Classifier: Programming Language :: Python :: 3
Classifier: Programming Language :: Python :: 3.10
Classifier: Programming Language :: Python :: 3.11
Classifier: Programming Language :: Python :: 3.12
Classifier: Programming Language :: Python :: 3.13
Requires-Python: >=3.10
Requires-Dist: pipelex[anthropic,bedrock,google,google-genai]==0.15.4
Requires-Dist: pygithub==2.4.0
Provides-Extra: dev
Requires-Dist: boto3-stubs>=1.35.24; extra == 'dev'
Requires-Dist: mypy>=1.11.2; extra == 'dev'
Requires-Dist: pyright>=1.1.405; extra == 'dev'
Requires-Dist: pytest-asyncio>=0.24.0; extra == 'dev'
Requires-Dist: pytest-cov>=6.1.1; extra == 'dev'
Requires-Dist: pytest-mock>=3.14.0; extra == 'dev'
Requires-Dist: pytest-sugar>=1.0.0; extra == 'dev'
Requires-Dist: pytest>=9.0.1; extra == 'dev'
Requires-Dist: ruff>=0.6.8; extra == 'dev'
Requires-Dist: types-aioboto3[bedrock,bedrock-runtime]>=13.4.0; extra == 'dev'
Requires-Dist: types-aiofiles>=24.1.0.20240626; extra == 'dev'
Requires-Dist: types-markdown>=3.6.0.20240316; extra == 'dev'
Requires-Dist: types-networkx>=3.3.0.20241020; extra == 'dev'
Requires-Dist: types-openpyxl>=3.1.5.20250306; extra == 'dev'
Requires-Dist: types-pyyaml>=6.0.12.20250326; extra == 'dev'
Provides-Extra: docs
Requires-Dist: mkdocs-glightbox==0.4.0; extra == 'docs'
Requires-Dist: mkdocs-material==9.6.14; extra == 'docs'
Requires-Dist: mkdocs-meta-manager==1.1.0; extra == 'docs'
Requires-Dist: mkdocs==1.6.1; extra == 'docs'
